proxy_inference_engine/__init__.py
proxy_inference_engine/cache/__init__.py
proxy_inference_engine/cache/prompt_cache.py
proxy_inference_engine/cache/kv_cache/__init__.py
proxy_inference_engine/cache/kv_cache/cache.py
proxy_inference_engine/cache/kv_cache/quantized.py
proxy_inference_engine/cache/kv_cache/reusable.py
proxy_inference_engine/cache/kv_cache/rotating.py
proxy_inference_engine/engine/__init__.py
proxy_inference_engine/engine/inference_engine.py
proxy_inference_engine/interaction/__init__.py
proxy_inference_engine/interaction/content.py
proxy_inference_engine/interaction/interaction.py
proxy_inference_engine/logits_processors/__init__.py
proxy_inference_engine/logits_processors/repetition.py
proxy_inference_engine/models/__init__.py
proxy_inference_engine/models/base.py
proxy_inference_engine/models/utils.py
proxy_inference_engine/models/gemma/__init__.py
proxy_inference_engine/models/gemma/ensemble.py
proxy_inference_engine/models/gemma/language.py
proxy_inference_engine/models/gemma/vision.py
proxy_inference_engine/models/intern/__init__.py
proxy_inference_engine/models/intern/ensemble.py
proxy_inference_engine/models/intern/language.py
proxy_inference_engine/models/intern/vision.py
proxy_inference_engine/samplers/__init__.py
proxy_inference_engine/samplers/categorical.py
proxy_inference_engine/samplers/dry.py
proxy_inference_engine/samplers/min_p.py
proxy_inference_engine/samplers/top_k.py
proxy_inference_engine/samplers/top_p.py
proxy_inference_engine/samplers/xtc.py
proxy_inference_engine/server/__init__.py
proxy_inference_engine/server/__main__.py
proxy_inference_engine/server/app.py
proxy_inference_engine/server/config.py
proxy_inference_engine/server/dependencies.py
proxy_inference_engine/server/exceptions.py
proxy_inference_engine/server/models/__init__.py
proxy_inference_engine/server/models/chat.py
proxy_inference_engine/server/models/completions.py
proxy_inference_engine/server/models/responses/__init__.py
proxy_inference_engine-0.2.0.dist-info/METADATA
proxy_inference_engine-0.2.0.dist-info/WHEEL
proxy_inference_engine-0.2.0.dist-info/top_level.txt
proxy_inference_engine-0.2.0.dist-info/RECORD
