Metadata-Version: 2.4
Name: proxy-inference-engine
Version: 0.2.0
Summary: Optimized LLM & MLX inference for Apple Silicon.
Author-email: The Proxy Company <info@theproxy.co>
License: MIT
Project-URL: Homepage, https://github.com/TheProxyCompany/proxy-inference-engine
Project-URL: Bug Tracker, https://github.com/TheProxyCompany/proxy-inference-engine/issues
Project-URL: Documentation, https://github.com/TheProxyCompany/proxy-inference-engine
Keywords: mlx,inference,llm,apple,vision,language,model,ai,proxy
Classifier: Development Status :: 4 - Beta
Classifier: Intended Audience :: Developers
Classifier: Intended Audience :: Science/Research
Classifier: License :: OSI Approved :: MIT License
Classifier: Programming Language :: Python :: 3
Classifier: Programming Language :: Python :: 3.12
Classifier: Topic :: Scientific/Engineering :: Artificial Intelligence
Classifier: Operating System :: MacOS :: MacOS X
Requires-Python: >=3.12
Requires-Dist: pse
Requires-Dist: mlx_lm
Requires-Dist: mlx
Requires-Dist: pillow
Requires-Dist: requests
Requires-Dist: transformers
Requires-Dist: huggingface-hub
Requires-Dist: fastapi[standard]
Requires-Dist: pydantic-settings
Provides-Extra: dev
Requires-Dist: black; extra == "dev"
Requires-Dist: isort; extra == "dev"
Requires-Dist: mypy; extra == "dev"
Requires-Dist: pytest; extra == "dev"
Requires-Dist: build; extra == "dev"
Requires-Dist: twine; extra == "dev"
Requires-Dist: ruff; extra == "dev"
